ngram_search/__init__.py
ngram_search/_search.cpython-35m-darwin.so
ngram_search-0.1.2.dist-info/LICENSE
ngram_search-0.1.2.dist-info/METADATA
ngram_search-0.1.2.dist-info/WHEEL
ngram_search-0.1.2.dist-info/top_level.txt
ngram_search-0.1.2.dist-info/RECORD
