Metadata-Version: 2.1
Name: ngram-search
Version: 0.1.2
Summary: Ngram-based indexing of strings into a binary file
Home-page: UNKNOWN
Author: Remi Rampin
Author-email: remirampin@gmail.com
License: MIT
Project-URL: Homepage, https://github.com/remram44/ngram-search
Project-URL: Source, https://github.com/remram44/ngram-search
Project-URL: Tracker, https://github.com/remram44/ngram-search/issues
Keywords: ngram,indexing,full-text,text-search,full-text-search
Platform: UNKNOWN
Classifier: Development Status :: 3 - Alpha
Classifier: Intended Audience :: Developers
Classifier: License :: OSI Approved :: MIT License
Classifier: Programming Language :: Cython
Classifier: Topic :: Database
Classifier: Topic :: Text Processing
